gitleaks_installer/__init__.py
gitleaks_installer/installer.py
gitleak_package-0.4.dist-info/METADATA
gitleak_package-0.4.dist-info/WHEEL
gitleak_package-0.4.dist-info/entry_points.txt
gitleak_package-0.4.dist-info/top_level.txt
gitleak_package-0.4.dist-info/RECORD
