Metadata-Version: 2.1
Name: gitleak-package
Version: 0.4
Classifier: Programming Language :: Python :: 3
Classifier: Operating System :: OS Independent
Requires-Dist: trufflehog
